{"WOII": [{"q": "Waarom startte Hitler WOII?", "a": "Expansiedrang", "wrong": ["Democratie", "Vrede", "Kolonisatie"]}], "Hitler deel 1": [{"q": "Waarom WOI oorzaak WOII?", "a": "Versailles", "wrong": ["Honger", "Communisme", "Revolutie"]}], "Hitler deel 2": [{"q": "Wat gaf geallieerden overwicht?", "a": "Economie", "wrong": ["Magie", "Diplomatie", "Geen idee"]}], "Breendonk": [{"q": "Waarom nummer i.p.v naam?", "a": "Ontmenselijking", "wrong": ["Praktisch", "Taal", "Regel"]}], "Periodisering": [{"q": "Wat is een eeuw?", "a": "100 jaar", "wrong": ["50 jaar", "1000 jaar", "10 jaar"]}]}